openai_copilot/__init__.py
openai_copilot/agent.py
openai_copilot/cli.py
openai_copilot/llm.py
openai_copilot/output.py
openai_copilot-0.2.6.dist-info/LICENSE
openai_copilot-0.2.6.dist-info/METADATA
openai_copilot-0.2.6.dist-info/WHEEL
openai_copilot-0.2.6.dist-info/entry_points.txt
openai_copilot-0.2.6.dist-info/RECORD
