Metadata-Version: 2.1
Name: openai-copilot
Version: 0.2.6
Summary: OpenAI Copilot
Home-page: https://github.com/feiskyer/openai-copilot
Keywords: copilot,openai,chatgpt
Author: Pengfei Ni
Author-email: feiskyer@gmail.com
Requires-Python: >=3.10,<4
Classifier: Programming Language :: Python :: 3
Classifier: Programming Language :: Python :: 3.10
Classifier: Programming Language :: Python :: 3.11
Classifier: Programming Language :: Python :: 3.12
Requires-Dist: click (>=8.1.3)
Requires-Dist: google-api-python-client (>=2.85.0)
Requires-Dist: langchain (>=0.0.226)
Requires-Dist: langchain-experimental (>=0.0.37,<0.0.38)
Requires-Dist: openai (>=0.27.4,<1)
Requires-Dist: requests (>=2.31)
Requires-Dist: tiktoken (>=0.4,<0.6)
Project-URL: Repository, https://github.com/feiskyer/openai-copilot
